airflow/providers/apache/drill/__init__.py
airflow/providers/apache/drill/get_provider_info.py
airflow/providers/apache/drill/hooks/__init__.py
airflow/providers/apache/drill/hooks/drill.py
airflow/providers/apache/drill/operators/__init__.py
apache_airflow_providers_apache_drill-3.2.1.dist-info/entry_points.txt
apache_airflow_providers_apache_drill-3.2.1.dist-info/licenses/LICENSE
apache_airflow_providers_apache_drill-3.2.1.dist-info/licenses/NOTICE
apache_airflow_providers_apache_drill-3.2.1.dist-info/WHEEL
apache_airflow_providers_apache_drill-3.2.1.dist-info/METADATA
apache_airflow_providers_apache_drill-3.2.1.dist-info/RECORD
